kafka/__init__.py
kafka/admin_kafka.py
kafka/consumer.py
kafka/message_production.py
kafka/minio_sink.py
kafka/producer.py
kafka/server_funcs.py
river_segmentation/__init__.py
river_segmentation/connectors/__init__.py
river_segmentation/connectors/base.py
river_segmentation/connectors/kafka_connector.py
river_segmentation/connectors/kafka_producer_connector.py
river_segmentation/connectors/minio_connector.py
river_segmentation/connectors/timescale_connector.py
river_segmentation/models/__init__.py
river_segmentation/models/model.py
river_segmentation-0.2.0.dist-info/METADATA
river_segmentation-0.2.0.dist-info/WHEEL
river_segmentation-0.2.0.dist-info/top_level.txt
river_segmentation-0.2.0.dist-info/RECORD
